{
    "DesktopAudioDevice1": {
        "prev_ver": 503382018,
        "name": "Desktop Audio",
        "uuid": "ee5a7031-ea87-4e04-ade6-c5c8806d80c4",
        "id": "wasapi_output_capture",
        "versioned_id": "wasapi_output_capture",
        "settings": {
            "device_id": "{0.0.0.00000000}.{f4b835a6-29fb-4c2e-91a3-c45667137fd5}"
        },
        "mixers": 255,
        "sync": 0,
        "flags": 0,
        "volume": 1.0,
        "balance": 0.5,
        "enabled": true,
        "muted": false,
        "push-to-mute": false,
        "push-to-mute-delay": 0,
        "push-to-talk": false,
        "push-to-talk-delay": 0,
        "hotkeys": {
            "libobs.mute": [],
            "libobs.unmute": [],
            "libobs.push-to-mute": [],
            "libobs.push-to-talk": []
        },
        "deinterlace_mode": 0,
        "deinterlace_field_order": 0,
        "monitoring_type": 2,
        "private_settings": {}
    },
    "current_scene": "gameplay",
    "current_program_scene": "gameplay",
    "scene_order": [
        {
            "name": "gameplay"
        },
        {
            "name": "mappool"
        },
        {
            "name": "__discord_dsk"
        }
    ],
    "name": "Cookie Run",
    "groups": [
        {
            "prev_ver": 503382018,
            "name": "names",
            "uuid": "70231ad2-b25c-4df9-a984-c9c9cc6bb6e1",
            "id": "group",
            "versioned_id": "group",
            "settings": {
                "custom_size": true,
                "cx": 1214,
                "cy": 716,
                "id_counter": 0,
                "items": [
                    {
                        "name": "name_0",
                        "source_uuid": "83499b64-1bdf-4388-9c33-bcf00051baf3",
                        "visible": true,
                        "locked": true,
                        "rot": 0.0,
                        "pos": {
                            "x": 0.0,
                            "y": 0.0
                        },
                        "scale": {
                            "x": 1.0,
                            "y": 1.0
                        },
                        "align": 5,
                        "bounds_type": 0,
                        "bounds_align": 0,
                        "bounds_crop": false,
                        "bounds": {
                            "x": 0.0,
                            "y": 0.0
                        },
                        "crop_left": 0,
                        "crop_top": 0,
                        "crop_right": 0,
                        "crop_bottom": 0,
                        "id": 23,
                        "group_item_backup": false,
                        "scale_filter": "disable",
                        "blend_method": "default",
                        "blend_type": "normal",
                        "show_transition": {
                            "duration": 0
                        },
                        "hide_transition": {
                            "duration": 0
                        },
                        "private_settings": {}
                    },
                    {
                        "name": "name_1",
                        "source_uuid": "281af154-01b9-422d-958c-f53d448ff20d",
                        "visible": true,
                        "locked": true,
                        "rot": 0.0,
                        "pos": {
                            "x": 614.0,
                            "y": 0.0
                        },
                        "scale": {
                            "x": 1.0,
                            "y": 1.0
                        },
                        "align": 5,
                        "bounds_type": 0,
                        "bounds_align": 0,
                        "bounds_crop": false,
                        "bounds": {
                            "x": 0.0,
                            "y": 0.0
                        },
                        "crop_left": 0,
                        "crop_top": 0,
                        "crop_right": 0,
                        "crop_bottom": 0,
                        "id": 24,
                        "group_item_backup": false,
                        "scale_filter": "disable",
                        "blend_method": "default",
                        "blend_type": "normal",
                        "show_transition": {
                            "duration": 0
                        },
                        "hide_transition": {
                            "duration": 0
                        },
                        "private_settings": {}
                    },
                    {
                        "name": "name_2",
                        "source_uuid": "5896dad2-3322-4b1a-9024-21d2c82968a9",
                        "visible": true,
                        "locked": true,
                        "rot": 0.0,
                        "pos": {
                            "x": 0.0,
                            "y": 378.0
                        },
                        "scale": {
                            "x": 1.0,
                            "y": 1.0
                        },
                        "align": 5,
                        "bounds_type": 0,
                        "bounds_align": 0,
                        "bounds_crop": false,
                        "bounds": {
                            "x": 0.0,
                            "y": 0.0
                        },
                        "crop_left": 0,
                        "crop_top": 0,
                        "crop_right": 0,
                        "crop_bottom": 0,
                        "id": 25,
                        "group_item_backup": false,
                        "scale_filter": "disable",
                        "blend_method": "default",
                        "blend_type": "normal",
                        "show_transition": {
                            "duration": 0
                        },
                        "hide_transition": {
                            "duration": 0
                        },
                        "private_settings": {}
                    },
                    {
                        "name": "name_3",
                        "source_uuid": "3d82ba26-0fd3-4748-befd-41a62fd62bd5",
                        "visible": true,
                        "locked": true,
                        "rot": 0.0,
                        "pos": {
                            "x": 614.0,
                            "y": 378.0
                        },
                        "scale": {
                            "x": 1.0,
                            "y": 1.0
                        },
                        "align": 5,
                        "bounds_type": 0,
                        "bounds_align": 0,
                        "bounds_crop": false,
                        "bounds": {
                            "x": 0.0,
                            "y": 0.0
                        },
                        "crop_left": 0,
                        "crop_top": 0,
                        "crop_right": 0,
                        "crop_bottom": 0,
                        "id": 26,
                        "group_item_backup": false,
                        "scale_filter": "disable",
                        "blend_method": "default",
                        "blend_type": "normal",
                        "show_transition": {
                            "duration": 0
                        },
                        "hide_transition": {
                            "duration": 0
                        },
                        "private_settings": {}
                    }
                ]
            },
            "mixers": 0,
            "sync": 0,
            "flags": 0,
            "volume": 1.0,
            "balance": 0.5,
            "enabled": true,
            "muted": false,
            "push-to-mute": false,
            "push-to-mute-delay": 0,
            "push-to-talk": false,
            "push-to-talk-delay": 0,
            "hotkeys": {
                "libobs.show_scene_item.23": [],
                "libobs.hide_scene_item.23": [],
                "libobs.show_scene_item.24": [],
                "libobs.hide_scene_item.24": [],
                "libobs.show_scene_item.25": [],
                "libobs.hide_scene_item.25": [],
                "libobs.show_scene_item.26": [],
                "libobs.hide_scene_item.26": []
            },
            "deinterlace_mode": 0,
            "deinterlace_field_order": 0,
            "monitoring_type": 0,
            "private_settings": {}
        },
        {
            "prev_ver": 503382018,
            "name": "scores",
            "uuid": "b57f807e-c7a0-40b4-b289-0d2cd2d1e175",
            "id": "group",
            "versioned_id": "group",
            "settings": {
                "custom_size": true,
                "cx": 1214,
                "cy": 717,
                "id_counter": 0,
                "items": [
                    {
                        "name": "score_0",
                        "source_uuid": "56e59d54-7ef8-4717-9a88-706a94e4a415",
                        "visible": true,
                        "locked": true,
                        "rot": 0.0,
                        "pos": {
                            "x": 0.0,
                            "y": 0.0
                        },
                        "scale": {
                            "x": 1.0,
                            "y": 1.0
                        },
                        "align": 5,
                        "bounds_type": 0,
                        "bounds_align": 0,
                        "bounds_crop": false,
                        "bounds": {
                            "x": 0.0,
                            "y": 0.0
                        },
                        "crop_left": 0,
                        "crop_top": 0,
                        "crop_right": 0,
                        "crop_bottom": 0,
                        "id": 18,
                        "group_item_backup": false,
                        "scale_filter": "disable",
                        "blend_method": "default",
                        "blend_type": "normal",
                        "show_transition": {
                            "duration": 0
                        },
                        "hide_transition": {
                            "duration": 0
                        },
                        "private_settings": {}
                    },
                    {
                        "name": "score_1",
                        "source_uuid": "1be63fd9-b6bc-4e2f-acce-b94bae191df9",
                        "visible": true,
                        "locked": true,
                        "rot": 0.0,
                        "pos": {
                            "x": 614.0,
                            "y": 0.0
                        },
                        "scale": {
                            "x": 1.0,
                            "y": 1.0
                        },
                        "align": 5,
                        "bounds_type": 0,
                        "bounds_align": 0,
                        "bounds_crop": false,
                        "bounds": {
                            "x": 0.0,
                            "y": 0.0
                        },
                        "crop_left": 0,
                        "crop_top": 0,
                        "crop_right": 0,
                        "crop_bottom": 0,
                        "id": 19,
                        "group_item_backup": false,
                        "scale_filter": "disable",
                        "blend_method": "default",
                        "blend_type": "normal",
                        "show_transition": {
                            "duration": 0
                        },
                        "hide_transition": {
                            "duration": 0
                        },
                        "private_settings": {}
                    },
                    {
                        "name": "score_2",
                        "source_uuid": "a96aef06-f958-4a9e-bf53-2e37f3445f3d",
                        "visible": true,
                        "locked": true,
                        "rot": 0.0,
                        "pos": {
                            "x": 0.0,
                            "y": 379.0
                        },
                        "scale": {
                            "x": 1.0,
                            "y": 1.0
                        },
                        "align": 5,
                        "bounds_type": 0,
                        "bounds_align": 0,
                        "bounds_crop": false,
                        "bounds": {
                            "x": 0.0,
                            "y": 0.0
                        },
                        "crop_left": 0,
                        "crop_top": 0,
                        "crop_right": 0,
                        "crop_bottom": 0,
                        "id": 20,
                        "group_item_backup": false,
                        "scale_filter": "disable",
                        "blend_method": "default",
                        "blend_type": "normal",
                        "show_transition": {
                            "duration": 0
                        },
                        "hide_transition": {
                            "duration": 0
                        },
                        "private_settings": {}
                    },
                    {
                        "name": "score_3",
                        "source_uuid": "4851e9c6-2ec0-4587-864c-5df18f7f954f",
                        "visible": true,
                        "locked": true,
                        "rot": 0.0,
                        "pos": {
                            "x": 614.0,
                            "y": 379.0
                        },
                        "scale": {
                            "x": 1.0,
                            "y": 1.0
                        },
                        "align": 5,
                        "bounds_type": 0,
                        "bounds_align": 0,
                        "bounds_crop": false,
                        "bounds": {
                            "x": 0.0,
                            "y": 0.0
                        },
                        "crop_left": 0,
                        "crop_top": 0,
                        "crop_right": 0,
                        "crop_bottom": 0,
                        "id": 21,
                        "group_item_backup": false,
                        "scale_filter": "disable",
                        "blend_method": "default",
                        "blend_type": "normal",
                        "show_transition": {
                            "duration": 0
                        },
                        "hide_transition": {
                            "duration": 0
                        },
                        "private_settings": {}
                    }
                ]
            },
            "mixers": 0,
            "sync": 0,
            "flags": 0,
            "volume": 1.0,
            "balance": 0.5,
            "enabled": true,
            "muted": false,
            "push-to-mute": false,
            "push-to-mute-delay": 0,
            "push-to-talk": false,
            "push-to-talk-delay": 0,
            "hotkeys": {
                "libobs.show_scene_item.18": [],
                "libobs.hide_scene_item.18": [],
                "libobs.show_scene_item.19": [],
                "libobs.hide_scene_item.19": [],
                "libobs.show_scene_item.20": [],
                "libobs.hide_scene_item.20": [],
                "libobs.show_scene_item.21": [],
                "libobs.hide_scene_item.21": []
            },
            "deinterlace_mode": 0,
            "deinterlace_field_order": 0,
            "monitoring_type": 0,
            "private_settings": {}
        },
        {
            "prev_ver": 503382018,
            "name": "osu_client_Gc",
            "uuid": "81b18bdf-2659-46db-9390-78705286d742",
            "id": "group",
            "versioned_id": "group",
            "settings": {
                "id_counter": 0,
                "custom_size": true,
                "cx": 614,
                "cy": 376,
                "items": [
                    {
                        "name": "osu_3_gc",
                        "source_uuid": "bbcff1da-55a6-4f53-bd73-dfdcb20633d9",
                        "visible": true,
                        "locked": true,
                        "rot": 0.0,
                        "pos": {
                            "x": 614.0,
                            "y": 376.0
                        },
                        "scale": {
                            "x": 0.9375,
                            "y": 0.93888890743255615
                        },
                        "align": 5,
                        "bounds_type": 0,
                        "bounds_align": 0,
                        "bounds_crop": false,
                        "bounds": {
                            "x": 1.0,
                            "y": 1.0
                        },
                        "crop_left": 0,
                        "crop_top": 0,
                        "crop_right": 0,
                        "crop_bottom": 0,
                        "id": 37,
                        "group_item_backup": false,
                        "scale_filter": "disable",
                        "blend_method": "default",
                        "blend_type": "normal",
                        "show_transition": {
                            "duration": 0
                        },
                        "hide_transition": {
                            "duration": 0
                        },
                        "private_settings": {}
                    },
                    {
                        "name": "psu_2_gc_",
                        "source_uuid": "0670fb5d-6630-49fd-b7d6-d7f9c2c47dd9",
                        "visible": true,
                        "locked": true,
                        "rot": 0.0,
                        "pos": {
                            "x": 0.0,
                            "y": 376.0
                        },
                        "scale": {
                            "x": 0.9375,
                            "y": 0.93888890743255615
                        },
                        "align": 5,
                        "bounds_type": 0,
                        "bounds_align": 0,
                        "bounds_crop": false,
                        "bounds": {
                            "x": 1.0,
                            "y": 1.0
                        },
                        "crop_left": 0,
                        "crop_top": 0,
                        "crop_right": 0,
                        "crop_bottom": 0,
                        "id": 38,
                        "group_item_backup": false,
                        "scale_filter": "disable",
                        "blend_method": "default",
                        "blend_type": "normal",
                        "show_transition": {
                            "duration": 0
                        },
                        "hide_transition": {
                            "duration": 0
                        },
                        "private_settings": {}
                    },
                    {
                        "name": "osu_1_gc",
                        "source_uuid": "6658d26d-ec6f-4ad2-921e-72bd6c4cc43b",
                        "visible": true,
                        "locked": true,
                        "rot": 0.0,
                        "pos": {
                            "x": 614.0,
                            "y": 0.0
                        },
                        "scale": {
                            "x": 0.9375,
                            "y": 0.93888890743255615
                        },
                        "align": 5,
                        "bounds_type": 0,
                        "bounds_align": 0,
                        "bounds_crop": false,
                        "bounds": {
                            "x": 1.0,
                            "y": 1.0
                        },
                        "crop_left": 0,
                        "crop_top": 0,
                        "crop_right": 0,
                        "crop_bottom": 0,
                        "id": 39,
                        "group_item_backup": false,
                        "scale_filter": "disable",
                        "blend_method": "default",
                        "blend_type": "normal",
                        "show_transition": {
                            "duration": 0
                        },
                        "hide_transition": {
                            "duration": 0
                        },
                        "private_settings": {}
                    },
                    {
                        "name": "osu_0_gc",
                        "source_uuid": "b2f73e6b-a6b7-417a-9618-69c1e29fd884",
                        "visible": true,
                        "locked": true,
                        "rot": 0.0,
                        "pos": {
                            "x": 0.0,
                            "y": 0.0
                        },
                        "scale": {
                            "x": 0.9375,
                            "y": 0.93888890743255615
                        },
                        "align": 5,
                        "bounds_type": 0,
                        "bounds_align": 0,
                        "bounds_crop": false,
                        "bounds": {
                            "x": 1.0,
                            "y": 1.0
                        },
                        "crop_left": 0,
                        "crop_top": 0,
                        "crop_right": 0,
                        "crop_bottom": 0,
                        "id": 40,
                        "group_item_backup": false,
                        "scale_filter": "disable",
                        "blend_method": "default",
                        "blend_type": "normal",
                        "show_transition": {
                            "duration": 0
                        },
                        "hide_transition": {
                            "duration": 0
                        },
                        "private_settings": {}
                    }
                ]
            },
            "mixers": 0,
            "sync": 0,
            "flags": 0,
            "volume": 1.0,
            "balance": 0.5,
            "enabled": true,
            "muted": false,
            "push-to-mute": false,
            "push-to-mute-delay": 0,
            "push-to-talk": false,
            "push-to-talk-delay": 0,
            "hotkeys": {
                "libobs.show_scene_item.37": [],
                "libobs.hide_scene_item.37": [],
                "libobs.show_scene_item.38": [],
                "libobs.hide_scene_item.38": [],
                "libobs.show_scene_item.39": [],
                "libobs.hide_scene_item.39": [],
                "libobs.show_scene_item.40": [],
                "libobs.hide_scene_item.40": []
            },
            "deinterlace_mode": 0,
            "deinterlace_field_order": 0,
            "monitoring_type": 0,
            "private_settings": {}
        }
    ],
    "quick_transitions": [
        {
            "name": "Cut",
            "duration": 300,
            "hotkeys": [],
            "id": 7,
            "fade_to_black": false
        },
        {
            "name": "Fade",
            "duration": 300,
            "hotkeys": [],
            "id": 8,
            "fade_to_black": false
        },
        {
            "name": "Fade",
            "duration": 300,
            "hotkeys": [],
            "id": 9,
            "fade_to_black": true
        }
    ],
    "transitions": [
        {
            "name": "GO TO POOL",
            "id": "obs_stinger_transition",
            "settings": {
                "audio_fade_style": 1,
                "audio_monitoring": 2,
                "tp_type": 1,
                "track_matte_enabled": false,
                "transition_point": 74,
                "path": "C:/Users/daohe/AppData/Roaming/osu/tournaments/CRTOA/CRTOASTREAMSTUFF/GO TO POOL.mov",
                "hw_decode": true
            }
        },
        {
            "name": "GO TO MAIN",
            "id": "obs_stinger_transition",
            "settings": {
                "audio_fade_style": 1,
                "audio_monitoring": 2,
                "tp_type": 1,
                "transition_point": 74,
                "path": "C:/Users/daohe/AppData/Roaming/osu/tournaments/CRTOA/CRTOASTREAMSTUFF/GO TO MAIN.mov",
                "hw_decode": true
            }
        },
        {
            "name": "GO TO SUIJI",
            "id": "obs_stinger_transition",
            "settings": {
                "audio_fade_style": 1,
                "audio_monitoring": 2,
                "path": "D:/OSU/Cookie Run/GO TO SUIJI.mov",
                "tp_type": 1,
                "transition_point": 74
            }
        },
        {
            "name": "GO TO RAID",
            "id": "obs_stinger_transition",
            "settings": {
                "audio_fade_style": 1,
                "audio_monitoring": 2,
                "path": "D:/OSU/Cookie Run/GO TO RAID.mov",
                "tp_type": 1,
                "transition_point": 74
            }
        },
        {
            "name": "GO TO SHOWCASE",
            "id": "obs_stinger_transition",
            "settings": {
                "audio_fade_style": 1,
                "audio_monitoring": 2,
                "path": "D:/OSU/Cookie Run/GO TO SHOWCASE.mov",
                "tp_type": 1,
                "transition_point": 74
            }
        }
    ],
    "saved_projectors": [],
    "current_transition": "GO TO SHOWCASE",
    "transition_duration": 300,
    "preview_locked": false,
    "scaling_enabled": false,
    "scaling_level": 0,
    "scaling_off_x": 0.0,
    "scaling_off_y": 0.0,
    "virtual-camera": {
        "type2": 3
    },
    "modules": {
        "decklink_captions": {
            "source": ""
        },
        "transition-table": {
            "transitions": [
                {
                    "from_scene": "Any",
                    "to_scene": "gameplay",
                    "transition": "GO TO MAIN",
                    "duration": 500
                },
                {
                    "from_scene": "Any",
                    "to_scene": "mappool",
                    "transition": "GO TO POOL",
                    "duration": 500
                }
            ],
            "dialog_width": 600,
            "dialog_height": 301,
            "enable_hotkey": [],
            "disable_hotkey": []
        },
        "scripts-tool": [],
        "output-timer": {
            "streamTimerHours": 0,
            "streamTimerMinutes": 0,
            "streamTimerSeconds": 30,
            "recordTimerHours": 0,
            "recordTimerMinutes": 0,
            "recordTimerSeconds": 30,
            "autoStartStreamTimer": false,
            "autoStartRecordTimer": false,
            "pauseRecordTimer": true
        },
        "auto-scene-switcher": {
            "interval": 300,
            "non_matching_scene": "",
            "switch_if_not_matching": false,
            "active": false,
            "switches": []
        },
        "captions": {
            "source": "",
            "enabled": false,
            "lang_id": 1033,
            "provider": "mssapi"
        },
        "downstream_keyers_channel": 7,
        "downstream_keyers": [
            {
                "name": "DSK 1",
                "transition": "",
                "transition_duration": 300,
                "show_transition": "",
                "show_transition_duration": 300,
                "hide_transition": "",
                "hide_transition_duration": 300,
                "scenes": [
                    {
                        "name": "__discord_dsk"
                    }
                ],
                "scene": "__discord_dsk",
                "null_hotkey": [],
                "enable_tie_hotkey": [],
                "disable_tie_hotkey": [],
                "exclude_scenes": []
            }
        ],
        "advanced-scene-switcher": {
            "sceneGroups": [],
            "macros": [],
            "macroProperties": {
                "highlightExecuted": false,
                "highlightConditions": false,
                "highlightActions": false,
                "newMacroRegisterHotkey": false
            },
            "variables": [],
            "switches": [],
            "ignoreWindows": [],
            "screenRegion": [],
            "pauseEntries": [],
            "sceneRoundTrip": [],
            "sceneTransitions": [],
            "defaultTransitions": [],
            "defTransitionDelay": 0,
            "ignoreIdleWindows": [],
            "idleTargetType": 0,
            "idleSceneName": "",
            "idleTransitionName": "",
            "idleEnable": false,
            "idleTime": 60,
            "executableSwitches": [],
            "randomSwitches": [],
            "fileSwitches": [],
            "readEnabled": false,
            "readPath": "",
            "writeEnabled": false,
            "writePath": "",
            "mediaSwitches": [],
            "timeSwitches": [],
            "audioSwitches": [],
            "audioFallbackTargetType": 0,
            "audioFallbackScene": "",
            "audioFallbackTransition": "",
            "audioFallbackEnable": false,
            "audioFallbackDuration": {
                "value": {
                    "value": 0.0,
                    "type": 0
                },
                "unit": 0,
                "version": 1
            },
            "videoSwitches": [],
            "ServerEnabled": false,
            "ServerPort": 55555,
            "LockToIPv4": false,
            "ClientEnabled": false,
            "Address": "",
            "ClientPort": 55555,
            "SendSceneChange": true,
            "SendSceneChangeAll": true,
            "SendPreview": true,
            "triggers": [],
            "interval": 300,
            "non_matching_scene": "",
            "switch_if_not_matching": 0,
            "noMatchDelay": {
                "value": {
                    "value": 0.0,
                    "type": 0
                },
                "unit": 0,
                "version": 1
            },
            "cooldown": {
                "value": {
                    "value": 0.0,
                    "type": 0
                },
                "unit": 0,
                "version": 1
            },
            "active": true,
            "startup_behavior": 0,
            "autoStartEvent": 0,
            "logLevel": 0,
            "showSystemTrayNotifications": false,
            "disableHints": false,
            "disableFilterComboboxFilter": false,
            "warnPluginLoadFailure": true,
            "hideLegacyTabs": true,
            "priority0": 10,
            "priority1": 0,
            "priority2": 2,
            "priority3": 8,
            "priority4": 6,
            "priority5": 9,
            "priority6": 7,
            "priority7": 4,
            "priority8": 1,
            "priority9": 5,
            "priority10": 3,
            "threadPriority": 3,
            "transitionOverrideOverride": false,
            "adjustActiveTransitionType": true,
            "lastImportPath": "",
            "startHotkey": [],
            "stopHotkey": [],
            "toggleHotkey": [],
            "upMacroSegmentHotkey": [],
            "downMacroSegmentHotkey": [],
            "removeMacroSegmentHotkey": [],
            "tabWidgetOrder": [
                {
                    "generalTab": 0
                },
                {
                    "macroTab": 1
                },
                {
                    "variableTab": 2
                },
                {
                    "windowTitleTab": 3
                },
                {
                    "executableTab": 4
                },
                {
                    "screenRegionTab": 5
                },
                {
                    "mediaTab": 6
                },
                {
                    "fileTab": 7
                },
                {
                    "randomTab": 8
                },
                {
                    "timeTab": 9
                },
                {
                    "idleTab": 10
                },
                {
                    "sceneSequenceTab": 11
                },
                {
                    "audioTab": 12
                },
                {
                    "videoTab": 13
                },
                {
                    "networkTab": 14
                },
                {
                    "sceneGroupTab": 15
                },
                {
                    "transitionsTab": 16
                },
                {
                    "pauseTab": 17
                },
                {
                    "sceneTriggerTab": 18
                }
            ],
            "saveWindowGeo": false,
            "windowPosX": 0,
            "windowPosY": 0,
            "windowWidth": 0,
            "windowHeight": 0,
            "macroListMacroEditSplitterPosition": [],
            "version": "cdacfc946c062982a5e865b9a4f849b5ce2fb05f",
            "websocketConnections": [],
            "twitchConnections": [],
            "actionQueues": []
        }
    },
    "sources": [
        {
            "prev_ver": 503382018,
            "name": "background",
            "uuid": "58781497-050f-4040-8ba2-48ba930c0ea8",
            "id": "image_source",
            "versioned_id": "image_source",
            "settings": {
                "file": "C:/Users/daohe/AppData/Roaming/osu/tournaments/CRTOA/CRTOASTREAMSTUFF/overlayBG.png"
            },
            "mixers": 0,
            "sync": 0,
            "flags": 0,
            "volume": 1.0,
            "balance": 0.5,
            "enabled": true,
            "muted": false,
            "push-to-mute": false,
            "push-to-mute-delay": 0,
            "push-to-talk": false,
            "push-to-talk-delay": 0,
            "hotkeys": {},
            "deinterlace_mode": 0,
            "deinterlace_field_order": 0,
            "monitoring_type": 0,
            "private_settings": {},
            "filters": [
                {
                    "prev_ver": 503382018,
                    "name": "Image Mask/Blend",
                    "uuid": "3a0aebfb-d3d2-4886-bf96-e2afec3e523c",
                    "id": "mask_filter",
                    "versioned_id": "mask_filter_v2",
                    "settings": {
                        "image_path": "C:/Users/daohe/AppData/Roaming/osu/tournaments/CRTOA/CRTOASTREAMSTUFF/MAINMASK.png",
                        "type": "mask_alpha_filter.effect"
                    },
                    "mixers": 0,
                    "sync": 0,
                    "flags": 0,
                    "volume": 1.0,
                    "balance": 0.5,
                    "enabled": true,
                    "muted": false,
                    "push-to-mute": false,
                    "push-to-mute-delay": 0,
                    "push-to-talk": false,
                    "push-to-talk-delay": 0,
                    "hotkeys": {},
                    "deinterlace_mode": 0,
                    "deinterlace_field_order": 0,
                    "monitoring_type": 0,
                    "private_settings": {}
                }
            ]
        },
        {
            "prev_ver": 503382018,
            "name": "discord audio",
            "uuid": "82f5e88e-02ed-4b5d-9900-3680b244489d",
            "id": "wasapi_output_capture",
            "versioned_id": "wasapi_output_capture",
            "settings": {
                "device_id": "{0.0.0.00000000}.{2dcdcbb3-12cf-45db-8983-8bf69e7c0b6c}"
            },
            "mixers": 255,
            "sync": 0,
            "flags": 0,
            "volume": 1.0,
            "balance": 0.5,
            "enabled": true,
            "muted": false,
            "push-to-mute": false,
            "push-to-mute-delay": 0,
            "push-to-talk": false,
            "push-to-talk-delay": 0,
            "hotkeys": {
                "libobs.mute": [],
                "libobs.unmute": [],
                "libobs.push-to-mute": [],
                "libobs.push-to-talk": []
            },
            "deinterlace_mode": 0,
            "deinterlace_field_order": 0,
            "monitoring_type": 0,
            "private_settings": {}
        },
        {
            "prev_ver": 503382018,
            "name": "gameplay",
            "uuid": "f1d16601-913b-480d-adb5-c64e4aadefff",
            "id": "scene",
            "versioned_id": "scene",
            "settings": {
                "custom_size": false,
                "id_counter": 41,
                "items": [
                    {
                        "name": "osu_3_gc",
                        "source_uuid": "bbcff1da-55a6-4f53-bd73-dfdcb20633d9",
                        "visible": true,
                        "locked": true,
                        "rot": 0.0,
                        "pos": {
                            "x": 644.0,
                            "y": 559.0
                        },
                        "scale": {
                            "x": 0.9375,
                            "y": 0.93888890743255615
                        },
                        "align": 5,
                        "bounds_type": 0,
                        "bounds_align": 0,
                        "bounds_crop": false,
                        "bounds": {
                            "x": 1.0,
                            "y": 1.0
                        },
                        "crop_left": 0,
                        "crop_top": 0,
                        "crop_right": 0,
                        "crop_bottom": 0,
                        "id": 37,
                        "group_item_backup": true,
                        "scale_filter": "disable",
                        "blend_method": "default",
                        "blend_type": "normal",
                        "show_transition": {
                            "duration": 0
                        },
                        "hide_transition": {
                            "duration": 0
                        },
                        "private_settings": {}
                    },
                    {
                        "name": "psu_2_gc_",
                        "source_uuid": "0670fb5d-6630-49fd-b7d6-d7f9c2c47dd9",
                        "visible": true,
                        "locked": true,
                        "rot": 0.0,
                        "pos": {
                            "x": 30.0,
                            "y": 559.0
                        },
                        "scale": {
                            "x": 0.9375,
                            "y": 0.93888890743255615
                        },
                        "align": 5,
                        "bounds_type": 0,
                        "bounds_align": 0,
                        "bounds_crop": false,
                        "bounds": {
                            "x": 1.0,
                            "y": 1.0
                        },
                        "crop_left": 0,
                        "crop_top": 0,
                        "crop_right": 0,
                        "crop_bottom": 0,
                        "id": 38,
                        "group_item_backup": true,
                        "scale_filter": "disable",
                        "blend_method": "default",
                        "blend_type": "normal",
                        "show_transition": {
                            "duration": 0
                        },
                        "hide_transition": {
                            "duration": 0
                        },
                        "private_settings": {}
                    },
                    {
                        "name": "osu_1_gc",
                        "source_uuid": "6658d26d-ec6f-4ad2-921e-72bd6c4cc43b",
                        "visible": true,
                        "locked": true,
                        "rot": 0.0,
                        "pos": {
                            "x": 644.0,
                            "y": 183.0
                        },
                        "scale": {
                            "x": 0.9375,
                            "y": 0.93888890743255615
                        },
                        "align": 5,
                        "bounds_type": 0,
                        "bounds_align": 0,
                        "bounds_crop": false,
                        "bounds": {
                            "x": 1.0,
                            "y": 1.0
                        },
                        "crop_left": 0,
                        "crop_top": 0,
                        "crop_right": 0,
                        "crop_bottom": 0,
                        "id": 39,
                        "group_item_backup": true,
                        "scale_filter": "disable",
                        "blend_method": "default",
                        "blend_type": "normal",
                        "show_transition": {
                            "duration": 0
                        },
                        "hide_transition": {
                            "duration": 0
                        },
                        "private_settings": {}
                    },
                    {
                        "name": "osu_0_gc",
                        "source_uuid": "b2f73e6b-a6b7-417a-9618-69c1e29fd884",
                        "visible": true,
                        "locked": true,
                        "rot": 0.0,
                        "pos": {
                            "x": 30.0,
                            "y": 183.0
                        },
                        "scale": {
                            "x": 0.9375,
                            "y": 0.93888890743255615
                        },
                        "align": 5,
                        "bounds_type": 0,
                        "bounds_align": 0,
                        "bounds_crop": false,
                        "bounds": {
                            "x": 1.0,
                            "y": 1.0
                        },
                        "crop_left": 0,
                        "crop_top": 0,
                        "crop_right": 0,
                        "crop_bottom": 0,
                        "id": 40,
                        "group_item_backup": true,
                        "scale_filter": "disable",
                        "blend_method": "default",
                        "blend_type": "normal",
                        "show_transition": {
                            "duration": 0
                        },
                        "hide_transition": {
                            "duration": 0
                        },
                        "private_settings": {}
                    },
                    {
                        "name": "osu_client_Gc",
                        "source_uuid": "81b18bdf-2659-46db-9390-78705286d742",
                        "visible": true,
                        "locked": true,
                        "rot": 0.0,
                        "pos": {
                            "x": 30.0,
                            "y": 183.0
                        },
                        "scale": {
                            "x": 1.0,
                            "y": 1.0
                        },
                        "align": 5,
                        "bounds_type": 0,
                        "bounds_align": 0,
                        "bounds_crop": false,
                        "bounds": {
                            "x": 0.0,
                            "y": 0.0
                        },
                        "crop_left": 0,
                        "crop_top": 0,
                        "crop_right": 0,
                        "crop_bottom": 0,
                        "id": 41,
                        "group_item_backup": false,
                        "scale_filter": "disable",
                        "blend_method": "default",
                        "blend_type": "normal",
                        "show_transition": {
                            "duration": 0
                        },
                        "hide_transition": {
                            "duration": 0
                        },
                        "private_settings": {}
                    },
                    {
                        "name": "background",
                        "source_uuid": "58781497-050f-4040-8ba2-48ba930c0ea8",
                        "visible": true,
                        "locked": true,
                        "rot": 0.0,
                        "pos": {
                            "x": 0.0,
                            "y": 0.0
                        },
                        "scale": {
                            "x": 1.0,
                            "y": 1.0
                        },
                        "align": 5,
                        "bounds_type": 0,
                        "bounds_align": 0,
                        "bounds_crop": false,
                        "bounds": {
                            "x": 0.0,
                            "y": 0.0
                        },
                        "crop_left": 0,
                        "crop_top": 0,
                        "crop_right": 0,
                        "crop_bottom": 0,
                        "id": 28,
                        "group_item_backup": false,
                        "scale_filter": "disable",
                        "blend_method": "default",
                        "blend_type": "normal",
                        "show_transition": {
                            "duration": 0
                        },
                        "hide_transition": {
                            "duration": 0
                        },
                        "private_settings": {}
                    },
                    {
                        "name": "name_0",
                        "source_uuid": "83499b64-1bdf-4388-9c33-bcf00051baf3",
                        "visible": true,
                        "locked": true,
                        "rot": 0.0,
                        "pos": {
                            "x": 30.0,
                            "y": 182.0
                        },
                        "scale": {
                            "x": 1.0,
                            "y": 1.0
                        },
                        "align": 5,
                        "bounds_type": 0,
                        "bounds_align": 0,
                        "bounds_crop": false,
                        "bounds": {
                            "x": 0.0,
                            "y": 0.0
                        },
                        "crop_left": 0,
                        "crop_top": 0,
                        "crop_right": 0,
                        "crop_bottom": 0,
                        "id": 23,
                        "group_item_backup": true,
                        "scale_filter": "disable",
                        "blend_method": "default",
                        "blend_type": "normal",
                        "show_transition": {
                            "duration": 0
                        },
                        "hide_transition": {
                            "duration": 0
                        },
                        "private_settings": {}
                    },
                    {
                        "name": "name_1",
                        "source_uuid": "281af154-01b9-422d-958c-f53d448ff20d",
                        "visible": true,
                        "locked": true,
                        "rot": 0.0,
                        "pos": {
                            "x": 644.0,
                            "y": 182.0
                        },
                        "scale": {
                            "x": 1.0,
                            "y": 1.0
                        },
                        "align": 5,
                        "bounds_type": 0,
                        "bounds_align": 0,
                        "bounds_crop": false,
                        "bounds": {
                            "x": 0.0,
                            "y": 0.0
                        },
                        "crop_left": 0,
                        "crop_top": 0,
                        "crop_right": 0,
                        "crop_bottom": 0,
                        "id": 24,
                        "group_item_backup": true,
                        "scale_filter": "disable",
                        "blend_method": "default",
                        "blend_type": "normal",
                        "show_transition": {
                            "duration": 0
                        },
                        "hide_transition": {
                            "duration": 0
                        },
                        "private_settings": {}
                    },
                    {
                        "name": "name_2",
                        "source_uuid": "5896dad2-3322-4b1a-9024-21d2c82968a9",
                        "visible": true,
                        "locked": true,
                        "rot": 0.0,
                        "pos": {
                            "x": 30.0,
                            "y": 560.0
                        },
                        "scale": {
                            "x": 1.0,
                            "y": 1.0
                        },
                        "align": 5,
                        "bounds_type": 0,
                        "bounds_align": 0,
                        "bounds_crop": false,
                        "bounds": {
                            "x": 0.0,
                            "y": 0.0
                        },
                        "crop_left": 0,
                        "crop_top": 0,
                        "crop_right": 0,
                        "crop_bottom": 0,
                        "id": 25,
                        "group_item_backup": true,
                        "scale_filter": "disable",
                        "blend_method": "default",
                        "blend_type": "normal",
                        "show_transition": {
                            "duration": 0
                        },
                        "hide_transition": {
                            "duration": 0
                        },
                        "private_settings": {}
                    },
                    {
                        "name": "name_3",
                        "source_uuid": "3d82ba26-0fd3-4748-befd-41a62fd62bd5",
                        "visible": true,
                        "locked": true,
                        "rot": 0.0,
                        "pos": {
                            "x": 644.0,
                            "y": 560.0
                        },
                        "scale": {
                            "x": 1.0,
                            "y": 1.0
                        },
                        "align": 5,
                        "bounds_type": 0,
                        "bounds_align": 0,
                        "bounds_crop": false,
                        "bounds": {
                            "x": 0.0,
                            "y": 0.0
                        },
                        "crop_left": 0,
                        "crop_top": 0,
                        "crop_right": 0,
                        "crop_bottom": 0,
                        "id": 26,
                        "group_item_backup": true,
                        "scale_filter": "disable",
                        "blend_method": "default",
                        "blend_type": "normal",
                        "show_transition": {
                            "duration": 0
                        },
                        "hide_transition": {
                            "duration": 0
                        },
                        "private_settings": {}
                    },
                    {
                        "name": "names",
                        "source_uuid": "70231ad2-b25c-4df9-a984-c9c9cc6bb6e1",
                        "visible": true,
                        "locked": true,
                        "rot": 0.0,
                        "pos": {
                            "x": 30.0,
                            "y": 182.0
                        },
                        "scale": {
                            "x": 1.0,
                            "y": 1.0
                        },
                        "align": 5,
                        "bounds_type": 0,
                        "bounds_align": 0,
                        "bounds_crop": false,
                        "bounds": {
                            "x": 0.0,
                            "y": 0.0
                        },
                        "crop_left": 0,
                        "crop_top": 0,
                        "crop_right": 0,
                        "crop_bottom": 0,
                        "id": 27,
                        "group_item_backup": false,
                        "scale_filter": "disable",
                        "blend_method": "default",
                        "blend_type": "normal",
                        "show_transition": {
                            "duration": 0
                        },
                        "hide_transition": {
                            "duration": 0
                        },
                        "private_settings": {
                            "collapsed": true
                        }
                    },
                    {
                        "name": "main_overlay",
                        "source_uuid": "5600aba6-c747-4ba9-bbda-41b91a128b09",
                        "visible": true,
                        "locked": true,
                        "rot": 0.0,
                        "pos": {
                            "x": 0.0,
                            "y": 0.0
                        },
                        "scale": {
                            "x": 1.0,
                            "y": 1.0
                        },
                        "align": 5,
                        "bounds_type": 0,
                        "bounds_align": 0,
                        "bounds_crop": false,
                        "bounds": {
                            "x": 0.0,
                            "y": 0.0
                        },
                        "crop_left": 0,
                        "crop_top": 0,
                        "crop_right": 0,
                        "crop_bottom": 0,
                        "id": 7,
                        "group_item_backup": false,
                        "scale_filter": "disable",
                        "blend_method": "default",
                        "blend_type": "normal",
                        "show_transition": {
                            "duration": 0
                        },
                        "hide_transition": {
                            "duration": 0
                        },
                        "private_settings": {}
                    },
                    {
                        "name": "score_0",
                        "source_uuid": "56e59d54-7ef8-4717-9a88-706a94e4a415",
                        "visible": true,
                        "locked": true,
                        "rot": 0.0,
                        "pos": {
                            "x": 30.0,
                            "y": 182.0
                        },
                        "scale": {
                            "x": 1.0,
                            "y": 1.0
                        },
                        "align": 5,
                        "bounds_type": 0,
                        "bounds_align": 0,
                        "bounds_crop": false,
                        "bounds": {
                            "x": 0.0,
                            "y": 0.0
                        },
                        "crop_left": 0,
                        "crop_top": 0,
                        "crop_right": 0,
                        "crop_bottom": 0,
                        "id": 18,
                        "group_item_backup": true,
                        "scale_filter": "disable",
                        "blend_method": "default",
                        "blend_type": "normal",
                        "show_transition": {
                            "duration": 0
                        },
                        "hide_transition": {
                            "duration": 0
                        },
                        "private_settings": {}
                    },
                    {
                        "name": "score_1",
                        "source_uuid": "1be63fd9-b6bc-4e2f-acce-b94bae191df9",
                        "visible": true,
                        "locked": true,
                        "rot": 0.0,
                        "pos": {
                            "x": 644.0,
                            "y": 182.0
                        },
                        "scale": {
                            "x": 1.0,
                            "y": 1.0
                        },
                        "align": 5,
                        "bounds_type": 0,
                        "bounds_align": 0,
                        "bounds_crop": false,
                        "bounds": {
                            "x": 0.0,
                            "y": 0.0
                        },
                        "crop_left": 0,
                        "crop_top": 0,
                        "crop_right": 0,
                        "crop_bottom": 0,
                        "id": 19,
                        "group_item_backup": true,
                        "scale_filter": "disable",
                        "blend_method": "default",
                        "blend_type": "normal",
                        "show_transition": {
                            "duration": 0
                        },
                        "hide_transition": {
                            "duration": 0
                        },
                        "private_settings": {}
                    },
                    {
                        "name": "score_2",
                        "source_uuid": "a96aef06-f958-4a9e-bf53-2e37f3445f3d",
                        "visible": true,
                        "locked": true,
                        "rot": 0.0,
                        "pos": {
                            "x": 30.0,
                            "y": 561.0
                        },
                        "scale": {
                            "x": 1.0,
                            "y": 1.0
                        },
                        "align": 5,
                        "bounds_type": 0,
                        "bounds_align": 0,
                        "bounds_crop": false,
                        "bounds": {
                            "x": 0.0,
                            "y": 0.0
                        },
                        "crop_left": 0,
                        "crop_top": 0,
                        "crop_right": 0,
                        "crop_bottom": 0,
                        "id": 20,
                        "group_item_backup": true,
                        "scale_filter": "disable",
                        "blend_method": "default",
                        "blend_type": "normal",
                        "show_transition": {
                            "duration": 0
                        },
                        "hide_transition": {
                            "duration": 0
                        },
                        "private_settings": {}
                    },
                    {
                        "name": "score_3",
                        "source_uuid": "4851e9c6-2ec0-4587-864c-5df18f7f954f",
                        "visible": true,
                        "locked": true,
                        "rot": 0.0,
                        "pos": {
                            "x": 644.0,
                            "y": 561.0
                        },
                        "scale": {
                            "x": 1.0,
                            "y": 1.0
                        },
                        "align": 5,
                        "bounds_type": 0,
                        "bounds_align": 0,
                        "bounds_crop": false,
                        "bounds": {
                            "x": 0.0,
                            "y": 0.0
                        },
                        "crop_left": 0,
                        "crop_top": 0,
                        "crop_right": 0,
                        "crop_bottom": 0,
                        "id": 21,
                        "group_item_backup": true,
                        "scale_filter": "disable",
                        "blend_method": "default",
                        "blend_type": "normal",
                        "show_transition": {
                            "duration": 0
                        },
                        "hide_transition": {
                            "duration": 0
                        },
                        "private_settings": {}
                    },
                    {
                        "name": "scores",
                        "source_uuid": "b57f807e-c7a0-40b4-b289-0d2cd2d1e175",
                        "visible": true,
                        "locked": true,
                        "rot": 0.0,
                        "pos": {
                            "x": 30.0,
                            "y": 182.0
                        },
                        "scale": {
                            "x": 1.0,
                            "y": 1.0
                        },
                        "align": 5,
                        "bounds_type": 0,
                        "bounds_align": 0,
                        "bounds_crop": false,
                        "bounds": {
                            "x": 0.0,
                            "y": 0.0
                        },
                        "crop_left": 0,
                        "crop_top": 0,
                        "crop_right": 0,
                        "crop_bottom": 0,
                        "id": 22,
                        "group_item_backup": false,
                        "scale_filter": "disable",
                        "blend_method": "default",
                        "blend_type": "normal",
                        "show_transition": {
                            "duration": 0
                        },
                        "hide_transition": {
                            "duration": 0
                        },
                        "private_settings": {
                            "collapsed": true
                        }
                    },
                    {
                        "name": "voice",
                        "source_uuid": "ac5601b1-da1f-4595-9e40-701dc1ed8d84",
                        "visible": true,
                        "locked": true,
                        "rot": 0.0,
                        "pos": {
                            "x": 1060.0,
                            "y": 0.0
                        },
                        "scale": {
                            "x": 1.0,
                            "y": 1.0
                        },
                        "align": 5,
                        "bounds_type": 0,
                        "bounds_align": 0,
                        "bounds_crop": false,
                        "bounds": {
                            "x": 0.0,
                            "y": 0.0
                        },
                        "crop_left": 0,
                        "crop_top": 0,
                        "crop_right": 0,
                        "crop_bottom": 0,
                        "id": 31,
                        "group_item_backup": false,
                        "scale_filter": "disable",
                        "blend_method": "default",
                        "blend_type": "normal",
                        "show_transition": {
                            "duration": 0
                        },
                        "hide_transition": {
                            "duration": 0
                        },
                        "private_settings": {}
                    }
                ]
            },
            "mixers": 0,
            "sync": 0,
            "flags": 0,
            "volume": 1.0,
            "balance": 0.5,
            "enabled": true,
            "muted": false,
            "push-to-mute": false,
            "push-to-mute-delay": 0,
            "push-to-talk": false,
            "push-to-talk-delay": 0,
            "hotkeys": {
                "OBSBasic.SelectScene": [],
                "libobs.show_scene_item.41": [],
                "libobs.hide_scene_item.41": [],
                "libobs.show_scene_item.28": [],
                "libobs.hide_scene_item.28": [],
                "libobs.show_scene_item.27": [],
                "libobs.hide_scene_item.27": [],
                "libobs.show_scene_item.7": [],
                "libobs.hide_scene_item.7": [],
                "libobs.show_scene_item.22": [],
                "libobs.hide_scene_item.22": [],
                "libobs.show_scene_item.31": [],
                "libobs.hide_scene_item.31": []
            },
            "deinterlace_mode": 0,
            "deinterlace_field_order": 0,
            "monitoring_type": 0,
            "private_settings": {
                "transition": "GO TO MAIN",
                "transition_duration": 500
            }
        },
        {
            "prev_ver": 503382018,
            "name": "mainbutpool",
            "uuid": "9d0531a9-8285-4f0a-985f-8e80bc508ae4",
            "id": "browser_source",
            "versioned_id": "browser_source",
            "settings": {
                "url": "http://127.0.0.1:24050/crtoa-stream-overlay/main/",
                "width": 2260,
                "height": 1080
            },
            "mixers": 255,
            "sync": 0,
            "flags": 0,
            "volume": 1.0,
            "balance": 0.5,
            "enabled": true,
            "muted": false,
            "push-to-mute": false,
            "push-to-mute-delay": 0,
            "push-to-talk": false,
            "push-to-talk-delay": 0,
            "hotkeys": {
                "libobs.mute": [],
                "libobs.unmute": [],
                "libobs.push-to-mute": [],
                "libobs.push-to-talk": [],
                "ObsBrowser.Refresh": []
            },
            "deinterlace_mode": 0,
            "deinterlace_field_order": 0,
            "monitoring_type": 0,
            "private_settings": {},
            "filters": [
                {
                    "prev_ver": 503382018,
                    "name": "Image Mask/Blend",
                    "uuid": "3c2c7c23-43cd-4a55-9b67-fbabea39fa8e",
                    "id": "mask_filter",
                    "versioned_id": "mask_filter_v2",
                    "settings": {
                        "image_path": "C:/Users/daohe/AppData/Roaming/osu/tournaments/CRTOA/CRTOASTREAMSTUFF/POOLMASK.png",
                        "type": "mask_alpha_filter.effect"
                    },
                    "mixers": 0,
                    "sync": 0,
                    "flags": 0,
                    "volume": 1.0,
                    "balance": 0.5,
                    "enabled": true,
                    "muted": false,
                    "push-to-mute": false,
                    "push-to-mute-delay": 0,
                    "push-to-talk": false,
                    "push-to-talk-delay": 0,
                    "hotkeys": {},
                    "deinterlace_mode": 0,
                    "deinterlace_field_order": 0,
                    "monitoring_type": 0,
                    "private_settings": {}
                }
            ]
        },
        {
            "prev_ver": 503382018,
            "name": "main_overlay",
            "uuid": "5600aba6-c747-4ba9-bbda-41b91a128b09",
            "id": "browser_source",
            "versioned_id": "browser_source",
            "settings": {
                "url": "http://127.0.0.1:24050/crtoa-stream-overlay/main/",
                "width": 2260,
                "height": 1080
            },
            "mixers": 255,
            "sync": 0,
            "flags": 0,
            "volume": 1.0,
            "balance": 0.5,
            "enabled": true,
            "muted": false,
            "push-to-mute": false,
            "push-to-mute-delay": 0,
            "push-to-talk": false,
            "push-to-talk-delay": 0,
            "hotkeys": {
                "libobs.mute": [],
                "libobs.unmute": [],
                "libobs.push-to-mute": [],
                "libobs.push-to-talk": [],
                "ObsBrowser.Refresh": []
            },
            "deinterlace_mode": 0,
            "deinterlace_field_order": 0,
            "monitoring_type": 0,
            "private_settings": {}
        },
        {
            "prev_ver": 503382018,
            "name": "mappool",
            "uuid": "a33a489b-d872-4176-bd83-fe90d2ade243",
            "id": "scene",
            "versioned_id": "scene",
            "settings": {
                "custom_size": false,
                "id_counter": 14,
                "items": [
                    {
                        "name": "mappool_overlay",
                        "source_uuid": "59a92328-3dfd-41a6-a272-ec6f0a71674c",
                        "visible": true,
                        "locked": true,
                        "rot": 0.0,
                        "pos": {
                            "x": 0.0,
                            "y": 0.0
                        },
                        "scale": {
                            "x": 1.0,
                            "y": 1.0
                        },
                        "align": 5,
                        "bounds_type": 0,
                        "bounds_align": 0,
                        "bounds_crop": false,
                        "bounds": {
                            "x": 0.0,
                            "y": 0.0
                        },
                        "crop_left": 0,
                        "crop_top": 0,
                        "crop_right": 0,
                        "crop_bottom": 0,
                        "id": 6,
                        "group_item_backup": false,
                        "scale_filter": "disable",
                        "blend_method": "default",
                        "blend_type": "normal",
                        "show_transition": {
                            "duration": 0
                        },
                        "hide_transition": {
                            "duration": 0
                        },
                        "private_settings": {}
                    },
                    {
                        "name": "mainbutpool",
                        "source_uuid": "9d0531a9-8285-4f0a-985f-8e80bc508ae4",
                        "visible": true,
                        "locked": true,
                        "rot": 0.0,
                        "pos": {
                            "x": 0.0,
                            "y": 0.0
                        },
                        "scale": {
                            "x": 1.0,
                            "y": 1.0
                        },
                        "align": 5,
                        "bounds_type": 0,
                        "bounds_align": 0,
                        "bounds_crop": false,
                        "bounds": {
                            "x": 0.0,
                            "y": 0.0
                        },
                        "crop_left": 0,
                        "crop_top": 0,
                        "crop_right": 1121,
                        "crop_bottom": 0,
                        "id": 10,
                        "group_item_backup": false,
                        "scale_filter": "disable",
                        "blend_method": "default",
                        "blend_type": "normal",
                        "show_transition": {
                            "duration": 0
                        },
                        "hide_transition": {
                            "duration": 0
                        },
                        "private_settings": {}
                    },
                    {
                        "name": "voice",
                        "source_uuid": "ac5601b1-da1f-4595-9e40-701dc1ed8d84",
                        "visible": true,
                        "locked": true,
                        "rot": 0.0,
                        "pos": {
                            "x": 1024.0,
                            "y": 0.0
                        },
                        "scale": {
                            "x": 1.0,
                            "y": 1.0
                        },
                        "align": 5,
                        "bounds_type": 0,
                        "bounds_align": 0,
                        "bounds_crop": false,
                        "bounds": {
                            "x": 0.0,
                            "y": 0.0
                        },
                        "crop_left": 0,
                        "crop_top": 0,
                        "crop_right": 0,
                        "crop_bottom": 0,
                        "id": 13,
                        "group_item_backup": false,
                        "scale_filter": "disable",
                        "blend_method": "default",
                        "blend_type": "normal",
                        "show_transition": {
                            "duration": 0
                        },
                        "hide_transition": {
                            "duration": 0
                        },
                        "private_settings": {}
                    }
                ]
            },
            "mixers": 0,
            "sync": 0,
            "flags": 0,
            "volume": 1.0,
            "balance": 0.5,
            "enabled": true,
            "muted": false,
            "push-to-mute": false,
            "push-to-mute-delay": 0,
            "push-to-talk": false,
            "push-to-talk-delay": 0,
            "hotkeys": {
                "OBSBasic.SelectScene": [],
                "libobs.show_scene_item.6": [],
                "libobs.hide_scene_item.6": [],
                "libobs.show_scene_item.10": [],
                "libobs.hide_scene_item.10": [],
                "libobs.show_scene_item.13": [],
                "libobs.hide_scene_item.13": []
            },
            "deinterlace_mode": 0,
            "deinterlace_field_order": 0,
            "monitoring_type": 0,
            "private_settings": {
                "transition": "GO TO POOL",
                "transition_duration": 500
            }
        },
        {
            "prev_ver": 503382018,
            "name": "mappool_overlay",
            "uuid": "59a92328-3dfd-41a6-a272-ec6f0a71674c",
            "id": "browser_source",
            "versioned_id": "browser_source",
            "settings": {
                "url": "http://127.0.0.1:24050/crtoa-stream-overlay/mappool/",
                "width": 2268,
                "height": 1080
            },
            "mixers": 255,
            "sync": 0,
            "flags": 0,
            "volume": 1.0,
            "balance": 0.5,
            "enabled": true,
            "muted": false,
            "push-to-mute": false,
            "push-to-mute-delay": 0,
            "push-to-talk": false,
            "push-to-talk-delay": 0,
            "hotkeys": {
                "libobs.mute": [],
                "libobs.unmute": [],
                "libobs.push-to-mute": [],
                "libobs.push-to-talk": [],
                "ObsBrowser.Refresh": []
            },
            "deinterlace_mode": 0,
            "deinterlace_field_order": 0,
            "monitoring_type": 0,
            "private_settings": {}
        },
        {
            "prev_ver": 503382018,
            "name": "name_0",
            "uuid": "83499b64-1bdf-4388-9c33-bcf00051baf3",
            "id": "browser_source",
            "versioned_id": "browser_source",
            "settings": {
                "url": "http://127.0.0.1:24050/crtoa-stream-overlay/names/?id=0&color=red&fontSize=36&placeholder=Waiting%20for%20P1...&flashBackground=true&align=left&debug=false",
                "width": 600,
                "height": 338
            },
            "mixers": 255,
            "sync": 0,
            "flags": 0,
            "volume": 1.0,
            "balance": 0.5,
            "enabled": true,
            "muted": false,
            "push-to-mute": false,
            "push-to-mute-delay": 0,
            "push-to-talk": false,
            "push-to-talk-delay": 0,
            "hotkeys": {
                "libobs.mute": [],
                "libobs.unmute": [],
                "libobs.push-to-mute": [],
                "libobs.push-to-talk": [],
                "ObsBrowser.Refresh": []
            },
            "deinterlace_mode": 0,
            "deinterlace_field_order": 0,
            "monitoring_type": 0,
            "private_settings": {}
        },
        {
            "prev_ver": 503382018,
            "name": "name_1",
            "uuid": "281af154-01b9-422d-958c-f53d448ff20d",
            "id": "browser_source",
            "versioned_id": "browser_source",
            "settings": {
                "url": "http://127.0.0.1:24050/crtoa-stream-overlay/names/?id=1&color=red&fontSize=36&placeholder=Waiting%20for%20P2...&flashBackground=true&align=right&debug=false",
                "width": 600,
                "height": 338
            },
            "mixers": 255,
            "sync": 0,
            "flags": 0,
            "volume": 1.0,
            "balance": 0.5,
            "enabled": true,
            "muted": false,
            "push-to-mute": false,
            "push-to-mute-delay": 0,
            "push-to-talk": false,
            "push-to-talk-delay": 0,
            "hotkeys": {
                "libobs.mute": [],
                "libobs.unmute": [],
                "libobs.push-to-mute": [],
                "libobs.push-to-talk": [],
                "ObsBrowser.Refresh": []
            },
            "deinterlace_mode": 0,
            "deinterlace_field_order": 0,
            "monitoring_type": 0,
            "private_settings": {}
        },
        {
            "prev_ver": 503382018,
            "name": "name_2",
            "uuid": "5896dad2-3322-4b1a-9024-21d2c82968a9",
            "id": "browser_source",
            "versioned_id": "browser_source",
            "settings": {
                "url": "http://127.0.0.1:24050/crtoa-stream-overlay/names/?id=2&color=blue&fontSize=36&placeholder=Waiting%20for%20P3...&flashBackground=true&align=left&debug=false",
                "width": 600,
                "height": 338
            },
            "mixers": 255,
            "sync": 0,
            "flags": 0,
            "volume": 1.0,
            "balance": 0.5,
            "enabled": true,
            "muted": false,
            "push-to-mute": false,
            "push-to-mute-delay": 0,
            "push-to-talk": false,
            "push-to-talk-delay": 0,
            "hotkeys": {
                "libobs.mute": [],
                "libobs.unmute": [],
                "libobs.push-to-mute": [],
                "libobs.push-to-talk": [],
                "ObsBrowser.Refresh": []
            },
            "deinterlace_mode": 0,
            "deinterlace_field_order": 0,
            "monitoring_type": 0,
            "private_settings": {}
        },
        {
            "prev_ver": 503382018,
            "name": "name_3",
            "uuid": "3d82ba26-0fd3-4748-befd-41a62fd62bd5",
            "id": "browser_source",
            "versioned_id": "browser_source",
            "settings": {
                "url": "http://127.0.0.1:24050/crtoa-stream-overlay/names/?id=3&color=blue&fontSize=36&placeholder=Waiting%20for%20P4...&flashBackground=true&align=right&debug=false",
                "width": 600,
                "height": 338
            },
            "mixers": 255,
            "sync": 0,
            "flags": 0,
            "volume": 1.0,
            "balance": 0.5,
            "enabled": true,
            "muted": false,
            "push-to-mute": false,
            "push-to-mute-delay": 0,
            "push-to-talk": false,
            "push-to-talk-delay": 0,
            "hotkeys": {
                "libobs.mute": [],
                "libobs.unmute": [],
                "libobs.push-to-mute": [],
                "libobs.push-to-talk": [],
                "ObsBrowser.Refresh": []
            },
            "deinterlace_mode": 0,
            "deinterlace_field_order": 0,
            "monitoring_type": 0,
            "private_settings": {}
        },
        {
            "prev_ver": 503382018,
            "name": "osu_0_gc",
            "uuid": "b2f73e6b-a6b7-417a-9618-69c1e29fd884",
            "id": "game_capture",
            "versioned_id": "game_capture",
            "settings": {
                "window": " Tournament Client 0:WindowsForms10.Window.2b.app.0.1ca0192_r8_ad1:osu!.exe",
                "capture_mode": "window",
                "priority": 1,
                "capture_cursor": false,
                "anti_cheat_hook": false
            },
            "mixers": 255,
            "sync": 0,
            "flags": 0,
            "volume": 1.0,
            "balance": 0.5,
            "enabled": true,
            "muted": false,
            "push-to-mute": false,
            "push-to-mute-delay": 0,
            "push-to-talk": false,
            "push-to-talk-delay": 0,
            "hotkeys": {
                "libobs.mute": [],
                "libobs.unmute": [],
                "libobs.push-to-mute": [],
                "libobs.push-to-talk": [],
                "hotkey_start": [],
                "hotkey_stop": []
            },
            "deinterlace_mode": 0,
            "deinterlace_field_order": 0,
            "monitoring_type": 0,
            "private_settings": {}
        },
        {
            "prev_ver": 503382018,
            "name": "osu_1_gc",
            "uuid": "6658d26d-ec6f-4ad2-921e-72bd6c4cc43b",
            "id": "game_capture",
            "versioned_id": "game_capture",
            "settings": {
                "window": " Tournament Client 1:WindowsForms10.Window.2b.app.0.1ca0192_r8_ad1:osu!.exe",
                "capture_mode": "window",
                "priority": 1,
                "capture_cursor": false,
                "anti_cheat_hook": false
            },
            "mixers": 255,
            "sync": 0,
            "flags": 0,
            "volume": 1.0,
            "balance": 0.5,
            "enabled": true,
            "muted": false,
            "push-to-mute": false,
            "push-to-mute-delay": 0,
            "push-to-talk": false,
            "push-to-talk-delay": 0,
            "hotkeys": {
                "libobs.mute": [],
                "libobs.unmute": [],
                "libobs.push-to-mute": [],
                "libobs.push-to-talk": [],
                "hotkey_start": [],
                "hotkey_stop": []
            },
            "deinterlace_mode": 0,
            "deinterlace_field_order": 0,
            "monitoring_type": 0,
            "private_settings": {}
        },
        {
            "prev_ver": 503382018,
            "name": "osu_3_gc",
            "uuid": "bbcff1da-55a6-4f53-bd73-dfdcb20633d9",
            "id": "game_capture",
            "versioned_id": "game_capture",
            "settings": {
                "window": " Tournament Client 3:WindowsForms10.Window.2b.app.0.1ca0192_r8_ad1:osu!.exe",
                "capture_mode": "window",
                "priority": 1,
                "capture_cursor": false,
                "anti_cheat_hook": false
            },
            "mixers": 255,
            "sync": 0,
            "flags": 0,
            "volume": 1.0,
            "balance": 0.5,
            "enabled": true,
            "muted": false,
            "push-to-mute": false,
            "push-to-mute-delay": 0,
            "push-to-talk": false,
            "push-to-talk-delay": 0,
            "hotkeys": {
                "libobs.mute": [],
                "libobs.unmute": [],
                "libobs.push-to-mute": [],
                "libobs.push-to-talk": [],
                "hotkey_start": [],
                "hotkey_stop": []
            },
            "deinterlace_mode": 0,
            "deinterlace_field_order": 0,
            "monitoring_type": 0,
            "private_settings": {}
        },
        {
            "prev_ver": 503382018,
            "name": "psu_2_gc_",
            "uuid": "0670fb5d-6630-49fd-b7d6-d7f9c2c47dd9",
            "id": "game_capture",
            "versioned_id": "game_capture",
            "settings": {
                "window": " Tournament Client 2:WindowsForms10.Window.2b.app.0.1ca0192_r8_ad1:osu!.exe",
                "capture_mode": "window",
                "priority": 1,
                "capture_cursor": false,
                "anti_cheat_hook": false
            },
            "mixers": 255,
            "sync": 0,
            "flags": 0,
            "volume": 1.0,
            "balance": 0.5,
            "enabled": true,
            "muted": false,
            "push-to-mute": false,
            "push-to-mute-delay": 0,
            "push-to-talk": false,
            "push-to-talk-delay": 0,
            "hotkeys": {
                "libobs.mute": [],
                "libobs.unmute": [],
                "libobs.push-to-mute": [],
                "libobs.push-to-talk": [],
                "hotkey_start": [],
                "hotkey_stop": []
            },
            "deinterlace_mode": 0,
            "deinterlace_field_order": 0,
            "monitoring_type": 0,
            "private_settings": {}
        },
        {
            "prev_ver": 503382018,
            "name": "score_0",
            "uuid": "56e59d54-7ef8-4717-9a88-706a94e4a415",
            "id": "browser_source",
            "versioned_id": "browser_source",
            "settings": {
                "url": "http://127.0.0.1:24050/crtoa-stream-overlay/scores/?id=0&fontSize=24&debug=false",
                "width": 600,
                "height": 338
            },
            "mixers": 255,
            "sync": 0,
            "flags": 0,
            "volume": 1.0,
            "balance": 0.5,
            "enabled": true,
            "muted": false,
            "push-to-mute": false,
            "push-to-mute-delay": 0,
            "push-to-talk": false,
            "push-to-talk-delay": 0,
            "hotkeys": {
                "libobs.mute": [],
                "libobs.unmute": [],
                "libobs.push-to-mute": [],
                "libobs.push-to-talk": [],
                "ObsBrowser.Refresh": []
            },
            "deinterlace_mode": 0,
            "deinterlace_field_order": 0,
            "monitoring_type": 0,
            "private_settings": {}
        },
        {
            "prev_ver": 503382018,
            "name": "score_1",
            "uuid": "1be63fd9-b6bc-4e2f-acce-b94bae191df9",
            "id": "browser_source",
            "versioned_id": "browser_source",
            "settings": {
                "url": "http://127.0.0.1:24050/crtoa-stream-overlay/scores/?id=1&fontSize=24&debug=false",
                "width": 600,
                "height": 338
            },
            "mixers": 255,
            "sync": 0,
            "flags": 0,
            "volume": 1.0,
            "balance": 0.5,
            "enabled": true,
            "muted": false,
            "push-to-mute": false,
            "push-to-mute-delay": 0,
            "push-to-talk": false,
            "push-to-talk-delay": 0,
            "hotkeys": {
                "libobs.mute": [],
                "libobs.unmute": [],
                "libobs.push-to-mute": [],
                "libobs.push-to-talk": [],
                "ObsBrowser.Refresh": []
            },
            "deinterlace_mode": 0,
            "deinterlace_field_order": 0,
            "monitoring_type": 0,
            "private_settings": {}
        },
        {
            "prev_ver": 503382018,
            "name": "score_2",
            "uuid": "a96aef06-f958-4a9e-bf53-2e37f3445f3d",
            "id": "browser_source",
            "versioned_id": "browser_source",
            "settings": {
                "url": "http://127.0.0.1:24050/crtoa-stream-overlay/scores/?id=2&fontSize=24&debug=false",
                "width": 600,
                "height": 338
            },
            "mixers": 255,
            "sync": 0,
            "flags": 0,
            "volume": 1.0,
            "balance": 0.5,
            "enabled": true,
            "muted": false,
            "push-to-mute": false,
            "push-to-mute-delay": 0,
            "push-to-talk": false,
            "push-to-talk-delay": 0,
            "hotkeys": {
                "libobs.mute": [],
                "libobs.unmute": [],
                "libobs.push-to-mute": [],
                "libobs.push-to-talk": [],
                "ObsBrowser.Refresh": []
            },
            "deinterlace_mode": 0,
            "deinterlace_field_order": 0,
            "monitoring_type": 0,
            "private_settings": {}
        },
        {
            "prev_ver": 503382018,
            "name": "score_3",
            "uuid": "4851e9c6-2ec0-4587-864c-5df18f7f954f",
            "id": "browser_source",
            "versioned_id": "browser_source",
            "settings": {
                "url": "http://127.0.0.1:24050/crtoa-stream-overlay/scores/?id=3&fontSize=24&debug=false",
                "width": 600,
                "height": 338
            },
            "mixers": 255,
            "sync": 0,
            "flags": 0,
            "volume": 1.0,
            "balance": 0.5,
            "enabled": true,
            "muted": false,
            "push-to-mute": false,
            "push-to-mute-delay": 0,
            "push-to-talk": false,
            "push-to-talk-delay": 0,
            "hotkeys": {
                "libobs.mute": [],
                "libobs.unmute": [],
                "libobs.push-to-mute": [],
                "libobs.push-to-talk": [],
                "ObsBrowser.Refresh": []
            },
            "deinterlace_mode": 0,
            "deinterlace_field_order": 0,
            "monitoring_type": 0,
            "private_settings": {}
        },
        {
            "prev_ver": 503382018,
            "name": "voice",
            "uuid": "ac5601b1-da1f-4595-9e40-701dc1ed8d84",
            "id": "browser_source",
            "versioned_id": "browser_source",
            "settings": {
                "url": "https://streamkit.discord.com/overlay/voice/1292748316622196757/1329756698692419604?icon=true&online=true&logo=white&text_color=%23ffffff&text_size=14&text_outline_color=%23000000&text_outline_size=0&text_shadow_color=%23000000&text_shadow_size=0&bg_color=%231e2124&bg_opacity=0.95&bg_shadow_color=%23000000&bg_shadow_size=0&invite_code=&limit_speaking=false&small_avatars=false&hide_names=false&fade_chat=0&streamer_avatar_first=false",
                "width": 1300,
                "css": "[class*=\"Voice_voiceStates__\"] {\n  flex-wrap: wrap;\n  display: flex;\n  margin: 32px;\n  column-gap: 18px;\n} \n[class*=\"Voice_voiceState__\"] {\n  height: auto;\n  margin-bottom: 0;\n  display: flex;\n  flex-direction: column;\n} \n[class*=\"Voice_avatar__\"] {\n  border-radius: 8px;\n  width: 80px;\n  height: 80px;\n  margin-bottom: 8px;\n  filter: brightness(70%);\n  margin-right: 0;\n} \n[class*=\"Voice_avatarSpeaking__\"] {\n  animation-duration: 750ms;\n  position: relative;\n  filter: brightness(100%);\n  border-color: rgb(255, 237, 190);\n  animation: 750ms infinite alternate ease-in-out speak-jump;\n  z-index: 1;\n} \n[class*=\"Voice_name__\"] {\n  left: 0px;\n  position: relative;\n  max-width: 86px;\n  z-index: 2;\n  box-sizing: border-box;\n  text-overflow: clip;\n  white-space: nowrap;\n  overflow: hidden;\n  display: block;\n  text-align: center;\n} \n[class*=\"Voice_user__\"] {\n  padding-top: 0px;\n}\n@keyframes speak-jump {\n  0% {\n    bottom: 0px;\n  }\n  50% {\n    bottom: 10px;\n  }\n  100% {\n    bottom: 0px;\n  }\n}\n@keyframes speak-border {\n  0% {\n    filter: drop-shadow(2px 2px 0px rgb(255, 236, 189)) drop-shadow(-2px -2px 0px rgb(255, 236, 189)) drop-shadow(-2px 2px 0px rgb(255, 236, 189)) drop-shadow(2px -2px 0px rgb(255, 236, 189));\n  }\n  50% {\n    filter: drop-shadow(2px 2px 0px rgb(255, 236, 189)) drop-shadow(-2px -2px 0px rgb(255, 236, 189)) drop-shadow(-2px 2px 0px rgb(255, 236, 189)) drop-shadow(2px -2px 0px rgb(255, 236, 189));\n  }\n  100% {\n    filter: drop-shadow(2px 2px 0px rgb(255, 236, 189)) drop-shadow(-2px -2px 0px rgb(255, 236, 189)) drop-shadow(-2px 2px 0px rgb(255, 236, 189)) drop-shadow(2px -2px 0px rgb(255, 236, 189));\n  }\n}"
            },
            "mixers": 255,
            "sync": 0,
            "flags": 0,
            "volume": 1.0,
            "balance": 0.5,
            "enabled": true,
            "muted": false,
            "push-to-mute": false,
            "push-to-mute-delay": 0,
            "push-to-talk": false,
            "push-to-talk-delay": 0,
            "hotkeys": {
                "libobs.mute": [],
                "libobs.unmute": [],
                "libobs.push-to-mute": [],
                "libobs.push-to-talk": [],
                "ObsBrowser.Refresh": []
            },
            "deinterlace_mode": 0,
            "deinterlace_field_order": 0,
            "monitoring_type": 0,
            "private_settings": {}
        },
        {
            "prev_ver": 503382018,
            "name": "__discord_dsk",
            "uuid": "59433221-5d7b-4fe5-9a61-30207e91c693",
            "id": "scene",
            "versioned_id": "scene",
            "settings": {
                "id_counter": 1,
                "custom_size": false,
                "items": [
                    {
                        "name": "discord audio",
                        "source_uuid": "82f5e88e-02ed-4b5d-9900-3680b244489d",
                        "visible": true,
                        "locked": false,
                        "rot": 0.0,
                        "pos": {
                            "x": 0.0,
                            "y": 0.0
                        },
                        "scale": {
                            "x": 1.0,
                            "y": 1.0
                        },
                        "align": 5,
                        "bounds_type": 0,
                        "bounds_align": 0,
                        "bounds_crop": false,
                        "bounds": {
                            "x": 0.0,
                            "y": 0.0
                        },
                        "crop_left": 0,
                        "crop_top": 0,
                        "crop_right": 0,
                        "crop_bottom": 0,
                        "id": 1,
                        "group_item_backup": false,
                        "scale_filter": "disable",
                        "blend_method": "default",
                        "blend_type": "normal",
                        "show_transition": {
                            "duration": 0
                        },
                        "hide_transition": {
                            "duration": 0
                        },
                        "private_settings": {}
                    }
                ]
            },
            "mixers": 0,
            "sync": 0,
            "flags": 0,
            "volume": 1.0,
            "balance": 0.5,
            "enabled": true,
            "muted": false,
            "push-to-mute": false,
            "push-to-mute-delay": 0,
            "push-to-talk": false,
            "push-to-talk-delay": 0,
            "hotkeys": {
                "OBSBasic.SelectScene": [],
                "libobs.show_scene_item.1": [],
                "libobs.hide_scene_item.1": [],
                "Show on DSK 1": [],
                "Hide on DSK 1": []
            },
            "deinterlace_mode": 0,
            "deinterlace_field_order": 0,
            "monitoring_type": 0,
            "private_settings": {}
        }
    ]
}